pyvmomi_tools/__init__.py
pyvmomi_tools/pchelper.py
pyvmomi_tools-0.1.2.dist-info/METADATA
pyvmomi_tools-0.1.2.dist-info/WHEEL
pyvmomi_tools-0.1.2.dist-info/RECORD
