Metadata-Version: 2.1
Name: pyvmomi-tools
Version: 0.1.2
Summary: 
Author: Blake
Author-email: 80996688+BlakeTnr@users.noreply.github.com
Requires-Python: >=3.12,<4.0
Classifier: Programming Language :: Python :: 3
Classifier: Programming Language :: Python :: 3.12
Requires-Dist: pyvmomi (>=8.0.2.0.1,<9.0.0.0.0)
